{
	"info": {
		"_postman_id": "0fb0a54a-1bca-4d2e-b79a-01c5b46bb2f6",
		"name": "findmyknife",
		"schema": "https://schema.getpostman.com/json/collection/v2.0.0/collection.json"
	},
	"item": [
		{
			"name": "localhost:5001/",
			"request": {
				"method": "GET",
				"header": [],
				"url": "localhost:5001/"
			},
			"response": []
		},
		{
			"name": "localhost:5001/product/B-0.2373.T",
			"request": {
				"method": "GET",
				"header": [],
				"url": "localhost:5001/product/B-0.2373.T"
			},
			"response": []
		},
		{
			"name": "host:5001/product/B-0.8413.M3",
			"request": {
				"method": "POST",
				"header": [
					{
						"key": "Content-Type",
						"value": "application/json"
					}
				],
				"body": {
					"mode": "raw",
					"raw": "{\n\t\"filters\": [\"scissor\", \"blade\"]\n}"
				},
				"url": "localhost:5001/product/B-0.8413.M3"
			},
			"response": []
		}
	]
}